.gitignore
.readthedocs.yml
.travis.yml
MANIFEST.in
README.rst
environment.yml
example.py
pyproject.toml
setup.cfg
setup.py
tox.ini
docs/Makefile
docs/conf.py
docs/index.rst
docs/make.bat
docs/_static/dot.css
docs/_static/dot.ico
docs/_static/dot.png
docs/_static/dot.svg
docs/dot/gettingstarted.rst
docs/dot/index.rst
docs/dot/plots.rst
dot/__init__.py
dot/_astropy_init.py
dot/conftest.py
dot/io.py
dot/model.py
dot/plots.py
dot/version.py
dot/data/README.rst
dot/data/abdor_lc_example.npy
dot/tests/__init__.py
dot/tests/test_model.py
dot/utils/__init__.py
dot/utils/tests/__init__.py
licenses/LICENSE.rst
licenses/README.rst
licenses/TEMPLATE_LICENCE.rst
spotdot.egg-info/PKG-INFO
spotdot.egg-info/SOURCES.txt
spotdot.egg-info/dependency_links.txt
spotdot.egg-info/not-zip-safe
spotdot.egg-info/requires.txt
spotdot.egg-info/top_level.txt