Metadata-Version: 2.1
Name: spotdot
Version: 0.1.2
Summary: Starspot rotational modulation forward model
Home-page: https://github.com/bmorris3/dot
Author: Brett M. Morris
Author-email: morrisbrettm@gmail.com
License: BSD 3-Clause
Platform: UNKNOWN
Requires-Python: >=3.6
Provides-Extra: test
Provides-Extra: docs
